pickle_rick/__init__.py
pickle_rick-1.2.4.dist-info/METADATA
pickle_rick-1.2.4.dist-info/WHEEL
pickle_rick-1.2.4.dist-info/RECORD
